{
  "$schema": "https://developer.microsoft.com/json-schemas/fabric/item/report/definition/visualContainer/2.8.0/schema.json",
  "name": "0d144b84e1004c970958",
  "position": {
    "x": 8,
    "y": 4.6082474226804209,
    "z": 0,
    "height": 27.75,
    "width": 24.75,
    "tabOrder": 1000
  },
  "visual": {
    "visualType": "image",
    "objects": {
      "image": [
        {
          "properties": {
            "sourceFile": {
              "image": {
                "name": {
                  "expr": {
                    "Literal": {
                      "Value": "'area-with-pins.png'"
                    }
                  }
                },
                "url": {
                  "expr": {
                    "ResourcePackageItem": {
                      "PackageName": "RegisteredResources",
                      "PackageType": 1,
                      "ItemName": "area-with-pins457226607556136.png"
                    }
                  }
                },
                "scaling": {
                  "expr": {
                    "Literal": {
                      "Value": "'Normal'"
                    }
                  }
                }
              }
            },
            "transparency": {
              "expr": {
                "Literal": {
                  "Value": "0D"
                }
              }
            }
          }
        }
      ]
    },
    "visualContainerObjects": {
      "visualLink": [
        {
          "properties": {
            "show": {
              "expr": {
                "Literal": {
                  "Value": "true"
                }
              }
            },
            "type": {
              "expr": {
                "Literal": {
                  "Value": "'PageNavigation'"
                }
              }
            },
            "navigationSection": {
              "expr": {
                "Literal": {
                  "Value": "''"
                }
              }
            }
          }
        }
      ]
    },
    "drillFilterOtherVisuals": true
  },
  "parentGroupName": "617a1915c0176080795c"
}